uavnoma/__init__.py
uavnoma/command_line.py
uavnoma/generate_values.py
uavnoma/performance_metrics.py
uavnoma-1.0.0.dist-info/LICENSE.txt
uavnoma-1.0.0.dist-info/METADATA
uavnoma-1.0.0.dist-info/WHEEL
uavnoma-1.0.0.dist-info/entry_points.txt
uavnoma-1.0.0.dist-info/top_level.txt
uavnoma-1.0.0.dist-info/RECORD
